pyvirtualdisplay/__init__.py
pyvirtualdisplay/about.py
pyvirtualdisplay/abstractdisplay.py
pyvirtualdisplay/display.py
pyvirtualdisplay/py.typed
pyvirtualdisplay/smartdisplay.py
pyvirtualdisplay/util.py
pyvirtualdisplay/xauth.py
pyvirtualdisplay/xephyr.py
pyvirtualdisplay/xvfb.py
pyvirtualdisplay/xvnc.py
pyvirtualdisplay/examples/__init__.py
pyvirtualdisplay/examples/headless.py
pyvirtualdisplay/examples/lowres.py
pyvirtualdisplay/examples/nested.py
pyvirtualdisplay/examples/screenshot.py
pyvirtualdisplay/examples/threadsafe.py
pyvirtualdisplay/examples/vncserver.py
PyVirtualDisplay-3.0.dist-info/LICENSE.txt
PyVirtualDisplay-3.0.dist-info/METADATA
PyVirtualDisplay-3.0.dist-info/WHEEL
PyVirtualDisplay-3.0.dist-info/top_level.txt
PyVirtualDisplay-3.0.dist-info/RECORD
