Metadata-Version: 2.1
Name: PyVirtualDisplay
Version: 3.0
Summary: python wrapper for Xvfb, Xephyr and Xvnc
Home-page: https://github.com/ponty/pyvirtualdisplay
Author: ponty
License: BSD
Keywords: Xvfb Xephyr X wrapper
Platform: UNKNOWN
Classifier: License :: OSI Approved :: BSD License
Classifier: Natural Language :: English
Classifier: Operating System :: OS Independent
Classifier: Programming Language :: Python
Classifier: Programming Language :: Python :: 3
Classifier: Programming Language :: Python :: 3 :: Only
Classifier: Programming Language :: Python :: 3.6
Classifier: Programming Language :: Python :: 3.7
Classifier: Programming Language :: Python :: 3.8
Classifier: Programming Language :: Python :: 3.9
Classifier: Programming Language :: Python :: 3.10
